LICENSE
README.md
setup.cfg
setup.py
certbot_dns_baidu/__init__.py
certbot_dns_baidu/dns_baidu.py
certbot_dns_baidu/dns_baidu_test.py
certbot_dns_baidu.egg-info/PKG-INFO
certbot_dns_baidu.egg-info/SOURCES.txt
certbot_dns_baidu.egg-info/dependency_links.txt
certbot_dns_baidu.egg-info/entry_points.txt
certbot_dns_baidu.egg-info/requires.txt
certbot_dns_baidu.egg-info/top_level.txt